network_utils/__init__.py
network_utils/wlt_brg_ota_location.py
wiliot_network_utils-1.0.1rc1.dist-info/licenses/LICENSE
wiliot_network_utils-1.0.1rc1.dist-info/METADATA
wiliot_network_utils-1.0.1rc1.dist-info/WHEEL
wiliot_network_utils-1.0.1rc1.dist-info/entry_points.txt
wiliot_network_utils-1.0.1rc1.dist-info/top_level.txt
wiliot_network_utils-1.0.1rc1.dist-info/RECORD
