Metadata-Version: 2.4
Name: wiliot_network_utils
Version: 1.0.1rc1
Summary: A library containing wiliot network utility scripts
Author-email: Wiliot <support@wiliot.com>
License: MIT License
Project-URL: Wiliot, https://www.wiliot.com
Classifier: Programming Language :: Python :: 3
Classifier: License :: OSI Approved :: MIT License
Classifier: Operating System :: OS Independent
Requires-Python: <3.10,>=3.9
License-File: LICENSE
Requires-Dist: wiliot_deployment_tools
Dynamic: license-file
